LICENSE
MANIFEST.in
README.rst
setup.py
pinyin_jyutping/__init__.py
pinyin_jyutping/cache.py
pinyin_jyutping/constants.py
pinyin_jyutping/conversion.py
pinyin_jyutping/data.py
pinyin_jyutping/dict.txt.big
pinyin_jyutping/errors.py
pinyin_jyutping/logic.py
pinyin_jyutping/parser.py
pinyin_jyutping/pinyin_jyutping.pkl
pinyin_jyutping/syllables.py
pinyin_jyutping.egg-info/PKG-INFO
pinyin_jyutping.egg-info/SOURCES.txt
pinyin_jyutping.egg-info/dependency_links.txt
pinyin_jyutping.egg-info/not-zip-safe
pinyin_jyutping.egg-info/requires.txt
pinyin_jyutping.egg-info/top_level.txt