Metadata-Version: 2.1
Name: pinyin-jyutping
Version: 0.7
Summary: Convert a Chinese sentence to Pinyin or Jyutping
Home-page: https://github.com/Language-Tools/pinyin-jyutping
Author: LucW
Author-email: languagetools@mailc.net
License: GPL
Classifier: Programming Language :: Python :: 3.7
Classifier: Programming Language :: Python :: 3.8
Classifier: Topic :: Text Processing :: Linguistic
License-File: LICENSE
